{
  "version": 1,
  "serviceConfiguration": {
    "serviceName": "AppSync",
    "defaultAuthType": {
      "mode": "API_KEY",
      "keyDescription": "api key description",
      "expirationTime": 30
    },
    "conflictResolution": {
      "defaultResolutionStrategy": {
        "type": "AUTOMERGE"
      }
    },
    "apiName": "thrifty",
    "gqlSchemaPath": "/tmp/amplify-cd186b2f-6ea8-4974-9b5c-2a7e84c2f9a1/amplify/backend/api/thrifty/schema.graphql",
    "additionalAuthTypes": [
      {
        "mode": "AWS_IAM"
      },
      {
        "mode": "AMAZON_COGNITO_USER_POOLS",
        "cognitoUserPoolId": "auththrifty21f6c364"
      }
    ]
  }
}